README.md
certbot-pdns.json
setup.cfg
setup.py
certbot_pdns/PdnsApiAuthenticator.py
certbot_pdns/__init__.py
certbot_pdns/authenticator.py
certbot_pdns/pdnsapi.py
certbot_pdns.egg-info/PKG-INFO
certbot_pdns.egg-info/SOURCES.txt
certbot_pdns.egg-info/dependency_links.txt
certbot_pdns.egg-info/entry_points.txt
certbot_pdns.egg-info/requires.txt
certbot_pdns.egg-info/top_level.txt