Metadata-Version: 1.1
Name: certbot-pdns
Version: 1.1.1
Summary: Certbot DNS authenticator
Home-page: https://git.rthoni.com/robin.thoni/certbot-pdns
Author: Robin Thoni
Author-email: robin@rthoni.com
License: MIT
Keywords: certbot authenticator plugin dns pdns powerdns api
Platform: UNKNOWN
Classifier: Development Status :: 5 - Production/Stable
Classifier: Intended Audience :: System Administrators
Classifier: Topic :: Internet :: Name Service (DNS)
Classifier: License :: OSI Approved :: MIT License
Classifier: Programming Language :: Python :: 2
Classifier: Programming Language :: Python :: 2.7
Classifier: Programming Language :: Python :: 3
Classifier: Programming Language :: Python :: 3.3
Classifier: Programming Language :: Python :: 3.4
Classifier: Programming Language :: Python :: 3.5
